s3watcher/__init__.py
s3watcher/s3_event.py
s3watcher/s3_watcher.py
python_s3watcher-0.1.dist-info/METADATA
python_s3watcher-0.1.dist-info/WHEEL
python_s3watcher-0.1.dist-info/top_level.txt
python_s3watcher-0.1.dist-info/RECORD
