Metadata-Version: 2.1
Name: python-s3watcher
Version: 0.1
Summary: A utility to watch file updates in a S3 folder.
Home-page: https://github.com/zzsi/s3watcher
Author: Zhangzhang Si
Author-email: zhangzhang.si@gmail.com
License: MIT
Requires-Python: >=3.6
Requires-Dist: boto3
